assignment_2/encoder_8to3.v
// 8-to-3 Encoder
module encoder_8to3 (
  input [7:0] in_data,
  output reg [2:0] out_code
);

  always @* begin
    case (in_data)
      8'b00000001: out_code = 3'b000;
      8'b00000010: out_code = 3'b001;
      8'b00000100: out_code = 3'b010;
      8'b00001000: out_code = 3'b011;
      8'b00010000: out_code = 3'b100;
      8'b00100000: out_code = 3'b101;
      8'b01000000: out_code = 3'b110;
      8'b10000000: out_code = 3'b111;
    endcase
  end
endmodule

assignment_2/tb_encoder_8to3.v
`include "encoder_8to3.v"
module tb_encoder;
reg [7:0] in_data;
wire [2:0] out_code;

// Instantiate the 8-to-3 encoder
encoder_8to3 obj(in_data,out_code);

initial begin
  $monitor("input=%b,output=%b\n", in_data,out_code);
    #2 in_data = 8'b00000001;
    #2 in_data = 8'b00000010;
    #2 in_data = 8'b00000100;
    #2 in_data = 8'b00001000;
    #2 in_data = 8'b00010000;
    #2 in_data = 8'b00100000;
    #2 in_data = 8'b01000000;
    #2 in_data = 8'b10000000;
end
initial begin
    $dumpfile("incode_out.vcd");
    $dumpvars;
    #100 $finish;
end
endmodule

assignment_2/incode_out.vcd
$date
	Sun Feb 25 15:35:25 2024
$end
$version
	Icarus Verilog
$end
$timescale
	1s
$end
$scope module tb_encoder $end
$var wire 3 ! out_code [2:0] $end
$var reg 8 " in_data [7:0] $end
$scope module obj $end
$var wire 8 # in_data [7:0] $end
$var reg 3 $ out_code [2:0] $end
$upscope $end
$upscope $end
$enddefinitions $end
#0
$dumpvars
bx $
bx #
bx "
bx !
$end
#2
b0 !
b0 $
b1 "
b1 #
#4
b1 !
b1 $
b10 "
b10 #
#6
b10 !
b10 $
b100 "
b100 #
#8
b11 !
b11 $
b1000 "
b1000 #
#10
b100 !
b100 $
b10000 "
b10000 #
#12
b101 !
b101 $
b100000 "
b100000 #
#14
b110 !
b110 $
b1000000 "
b1000000 #
#16
b111 !
b111 $
b10000000 "
b10000000 #
