assignment_2/decoder_3to8.v
// 3 -to-8 decoder
module decoder_3to8 (
  input [2:0] in_data,
  output reg [7:0] out_code
);
  always @* begin
    case(in_data)
      3'b000: out_code = 8'b00000001;
      3'b001: out_code = 8'b00000010;
      3'b010: out_code = 8'b00000100;
      3'b011: out_code = 8'b00001000;
      3'b100: out_code = 8'b00010000;
      3'b101: out_code = 8'b00100000;
      3'b110: out_code = 8'b01000000;
      3'b111: out_code = 8'b10000000;
    endcase
  end
endmodule

assignment_2/tb_decoder_3to8.v
`include "decoder_3to8.v"
module tb_decoder;
reg [2:0] in_data;
wire [7:0] out_code;

// Instantiate the 8-to-3 decoder
decoder_3to8 obj(in_data,out_code);

initial begin
  $monitor("input=%b,output=%b\n", in_data,out_code);
    #2 in_data = 3'b000;
    #2 in_data = 3'b001;
    #2 in_data = 3'b010;
    #2 in_data = 3'b100;
    #2 in_data = 3'b110;
    #2 in_data = 3'b101;
    #2 in_data = 3'b111;
    #2 in_data = 3'b011;   
end
initial begin
    $dumpfile("out.vcd");
    $dumpvars;
    #100 $finish;
end
endmodule

assignment_2/out.vcd
$date
	Sun Feb 25 15:55:19 2024
$end
$version
	Icarus Verilog
$end
$timescale
	1s
$end
$scope module tb_decoder $end
$var wire 8 ! out_code [7:0] $end
$var reg 3 " in_data [2:0] $end
$scope module obj $end
$var wire 3 # in_data [2:0] $end
$var reg 8 $ out_code [7:0] $end
$upscope $end
$upscope $end
$enddefinitions $end
#0
$dumpvars
bx $
bx #
bx "
bx !
$end
#2
b1 !
b1 $
b0 "
b0 #
#4
b10 !
b10 $
b1 "
b1 #
#6
b100 !
b100 $
b10 "
b10 #
#8
b10000 !
b10000 $
b100 "
b100 #
#10
b1000000 !
b1000000 $
b110 "
b110 #
#12
b100000 !
b100000 $
b101 "
b101 #
#14
b10000000 !
b10000000 $
b111 "
b111 #
#16
b1000 !
b1000 $
b11 "
b11 #
